{
  "package": "mmengine>=0.10.3",
  "apt_dependencies": [
    "python3",
    "python3-pip",
    "python3-dev",
    "build-essential",
    "libyaml-dev"
  ],
  "brew_dependencies": [
    "python3",
    "libyaml"
  ],
  "nix_dependencies": [
    "python3",
    "libyaml"
  ],
  "description": "System dependencies required for mmengine>=0.10.3 pip package",
  "notes": "MMEngine is OpenMMLab's foundational library for training deep learning models. It's primarily a pure Python package with minimal system dependencies. The main system dependency is libyaml for faster YAML parsing (used by PyYAML, one of mmengine's core dependencies). On Ubuntu/Debian, python3-dev and build-essential are needed for compiling C extensions from dependencies. On macOS with Homebrew and NixOS, libyaml is the primary requirement for optimal YAML performance. For most use cases with pre-built wheels, only python3 is strictly required at runtime, but libyaml significantly improves configuration file parsing performance which is important for deep learning workflows."
}
